README.rst
setup.py
pyegeg/__init__.py
pyegeg/parameters.py
pyegeg/spectran.py
pyegeg.egg-info/PKG-INFO
pyegeg.egg-info/SOURCES.txt
pyegeg.egg-info/dependency_links.txt
pyegeg.egg-info/requires.txt
pyegeg.egg-info/top_level.txt