Metadata-Version: 1.1
Name: pyegeg
Version: 0.5.0
Summary: Library for analysis of electrogastroenterograms
Home-page: https://bitbucket.org/lex_t/pyegeg
Author: Aleksandr Popov, Aleksey Tyulpin
Author-email: aleneus@gmail.com, alekseytyulpin@gmail.com
License: GPL
Keywords: electrogastroenterography electrogastrography python
Platform: Windows
Platform: Linux
Platform: Solaris
Platform: Mac OS-X
Platform: Unix
Classifier: Development Status :: 3 - Alpha
Classifier: Intended Audience :: Healthcare Industry
Classifier: Intended Audience :: Science/Research
Classifier: License :: OSI Approved :: GNU General Public License (GPL)
Classifier: Programming Language :: Python :: 3
Classifier: Programming Language :: Python :: 3.2
Classifier: Programming Language :: Python :: 3.3
Classifier: Programming Language :: Python :: 3.4
Classifier: Operating System :: OS Independent
Classifier: Topic :: Scientific/Engineering :: Medical Science Apps.
Classifier: Topic :: Scientific/Engineering :: Physics
Classifier: Topic :: Software Development :: Libraries
